MANIFEST.in
README.md
VERSION
setup.py
dirtemplate/__init__.py
dirtemplate/exceptions.py
dirtemplate/template.py
dirtemplate.egg-info/PKG-INFO
dirtemplate.egg-info/SOURCES.txt
dirtemplate.egg-info/dependency_links.txt
dirtemplate.egg-info/not-zip-safe
dirtemplate.egg-info/requires.txt
dirtemplate.egg-info/top_level.txt